LEAFeatures/__init__.py
LEAFeatures/leafs.py
LEAFeatures-0.2.0.dist-info/LICENSE
LEAFeatures-0.2.0.dist-info/METADATA
LEAFeatures-0.2.0.dist-info/WHEEL
LEAFeatures-0.2.0.dist-info/top_level.txt
LEAFeatures-0.2.0.dist-info/RECORD
