Metadata-Version: 2.1
Name: LEAFeatures
Version: 0.2.0
Summary: Local Enviroment-induced Atomic Features (LEAF)
Home-page: https://github.com/lrcfmd/LEAFs
Author: Andrij Vasylenko
License: MIT
License-File: LICENSE
Requires-Dist: adjustText (==1.3.0)
Requires-Dist: ase (==3.23.0)
Requires-Dist: ElMD (==0.5.14)
Requires-Dist: matminer (==0.9.0)
Requires-Dist: matplotlib
Requires-Dist: monty (==2024.5.24)
Requires-Dist: numpy (>=1.16)
Requires-Dist: pandas
Requires-Dist: plotly (==5.19.0)
Requires-Dist: pymatgen (==2024.5.31)
Requires-Dist: scikit-learn (==1.5.2)
Requires-Dist: scipy (==1.10.1)
Requires-Dist: seaborn (==0.13.2)
Requires-Dist: setuptools
Requires-Dist: SMACT (==2.5.3)
Requires-Dist: tqdm (==4.66.4)
